{
  "actions": [
    {
      "cost_ms": 600,
      "to": {
        "max": [
          2925,
          3440,
          0
        ],
        "min": [
          2925,
          3440,
          0
        ]
      },
      "type": "move"
    },
    {
      "cost_ms": 600,
      "to": {
        "max": [
          2925,
          3439,
          0
        ],
        "min": [
          2925,
          3439,
          0
        ]
      },
      "type": "move"
    },
    {
      "cost_ms": 600,
      "to": {
        "max": [
          2926,
          3439,
          0
        ],
        "min": [
          2926,
          3439,
          0
        ]
      },
      "type": "move"
    },
    {
      "cost_ms": 600,
      "to": {
        "max": [
          2927,
          3439,
          0
        ],
        "min": [
          2927,
          3439,
          0
        ]
      },
      "type": "move"
    },
    {
      "cost_ms": 600,
      "to": {
        "max": [
          2928,
          3439,
          0
        ],
        "min": [
          2928,
          3439,
          0
        ]
      },
      "type": "move"
    },
    {
      "cost_ms": 600,
      "to": {
        "max": [
          2929,
          3439,
          0
        ],
        "min": [
          2929,
          3439,
          0
        ]
      },
      "type": "move"
    },
    {
      "cost_ms": 600,
      "to": {
        "max": [
          2930,
          3439,
          0
        ],
        "min": [
          2930,
          3439,
          0
        ]
      },
      "type": "move"
    },
    {
      "cost_ms": 600,
      "to": {
        "max": [
          2931,
          3439,
          0
        ],
        "min": [
          2931,
          3439,
          0
        ]
      },
      "type": "move"
    },
    {
      "cost_ms": 600,
      "to": {
        "max": [
          2932,
          3439,
          0
        ],
        "min": [
          2932,
          3439,
          0
        ]
      },
      "type": "move"
    },
    {
      "cost_ms": 600,
      "to": {
        "max": [
          2933,
          3439,
          0
        ],
        "min": [
          2933,
          3439,
          0
        ]
      },
      "type": "move"
    },
    {
      "cost_ms": 600,
      "to": {
        "max": [
          2934,
          3439,
          0
        ],
        "min": [
          2934,
          3439,
          0
        ]
      },
      "type": "move"
    },
    {
      "cost_ms": 600,
      "to": {
        "max": [
          2935,
          3439,
          0
        ],
        "min": [
          2935,
          3439,
          0
        ]
      },
      "type": "move"
    },
    {
      "cost_ms": 600,
      "to": {
        "max": [
          2936,
          3439,
          0
        ],
        "min": [
          2936,
          3439,
          0
        ]
      },
      "type": "move"
    },
    {
      "cost_ms": 600,
      "to": {
        "max": [
          2937,
          3439,
          0
        ],
        "min": [
          2937,
          3439,
          0
        ]
      },
      "type": "move"
    },
    {
      "cost_ms": 600,
      "to": {
        "max": [
          2938,
          3439,
          0
        ],
        "min": [
          2938,
          3439,
          0
        ]
      },
      "type": "move"
    },
    {
      "cost_ms": 600,
      "to": {
        "max": [
          2939,
          3439,
          0
        ],
        "min": [
          2939,
          3439,
          0
        ]
      },
      "type": "move"
    },
    {
      "cost_ms": 600,
      "to": {
        "max": [
          2940,
          3439,
          0
        ],
        "min": [
          2940,
          3439,
          0
        ]
      },
      "type": "move"
    },
    {
      "cost_ms": 600,
      "to": {
        "max": [
          2941,
          3439,
          0
        ],
        "min": [
          2941,
          3439,
          0
        ]
      },
      "type": "move"
    },
    {
      "cost_ms": 600,
      "to": {
        "max": [
          2942,
          3439,
          0
        ],
        "min": [
          2942,
          3439,
          0
        ]
      },
      "type": "move"
    },
    {
      "cost_ms": 600,
      "edge_id": 2,
      "from": {
        "max": [
          2942,
          3439,
          0
        ],
        "min": [
          2942,
          3439,
          0
        ]
      },
      "metadata": {
        "db_row": {
          "cost": 600,
          "direction": null,
          "id": 2,
          "location_closed_plane": 0,
          "location_closed_x": 2942,
          "location_closed_y": 3439,
          "location_open_plane": 0,
          "location_open_x": 2943,
          "location_open_y": 3439,
          "next_node_id": null,
          "next_node_type": null,
          "open_action": "Open",
          "real_id_closed": 28690,
          "real_id_open": 28692,
          "requirement_id": null,
          "tile_inside_plane": 0,
          "tile_inside_x": 2942,
          "tile_inside_y": 3439,
          "tile_outside_plane": 0,
          "tile_outside_x": 2943,
          "tile_outside_y": 3439
        }
      },
      "node": {
        "id": 2,
        "type": "door"
      },
      "requirement_id": null,
      "to": {
        "max": [
          2943,
          3439,
          0
        ],
        "min": [
          2943,
          3439,
          0
        ]
      },
      "type": "door"
    },
    {
      "cost_ms": 600,
      "to": {
        "max": [
          2944,
          3439,
          0
        ],
        "min": [
          2944,
          3439,
          0
        ]
      },
      "type": "move"
    },
    {
      "cost_ms": 600,
      "to": {
        "max": [
          2945,
          3439,
          0
        ],
        "min": [
          2945,
          3439,
          0
        ]
      },
      "type": "move"
    },
    {
      "cost_ms": 600,
      "to": {
        "max": [
          2945,
          3438,
          0
        ],
        "min": [
          2945,
          3438,
          0
        ]
      },
      "type": "move"
    },
    {
      "cost_ms": 600,
      "to": {
        "max": [
          2945,
          3437,
          0
        ],
        "min": [
          2945,
          3437,
          0
        ]
      },
      "type": "move"
    },
    {
      "cost_ms": 600,
      "to": {
        "max": [
          2945,
          3436,
          0
        ],
        "min": [
          2945,
          3436,
          0
        ]
      },
      "type": "move"
    },
    {
      "cost_ms": 600,
      "to": {
        "max": [
          2945,
          3435,
          0
        ],
        "min": [
          2945,
          3435,
          0
        ]
      },
      "type": "move"
    },
    {
      "cost_ms": 600,
      "to": {
        "max": [
          2945,
          3434,
          0
        ],
        "min": [
          2945,
          3434,
          0
        ]
      },
      "type": "move"
    },
    {
      "cost_ms": 600,
      "to": {
        "max": [
          2945,
          3433,
          0
        ],
        "min": [
          2945,
          3433,
          0
        ]
      },
      "type": "move"
    },
    {
      "cost_ms": 600,
      "to": {
        "max": [
          2945,
          3432,
          0
        ],
        "min": [
          2945,
          3432,
          0
        ]
      },
      "type": "move"
    },
    {
      "cost_ms": 600,
      "to": {
        "max": [
          2945,
          3431,
          0
        ],
        "min": [
          2945,
          3431,
          0
        ]
      },
      "type": "move"
    },
    {
      "cost_ms": 600,
      "to": {
        "max": [
          2945,
          3430,
          0
        ],
        "min": [
          2945,
          3430,
          0
        ]
      },
      "type": "move"
    },
    {
      "cost_ms": 600,
      "to": {
        "max": [
          2945,
          3429,
          0
        ],
        "min": [
          2945,
          3429,
          0
        ]
      },
      "type": "move"
    },
    {
      "cost_ms": 600,
      "to": {
        "max": [
          2945,
          3428,
          0
        ],
        "min": [
          2945,
          3428,
          0
        ]
      },
      "type": "move"
    },
    {
      "cost_ms": 600,
      "to": {
        "max": [
          2945,
          3427,
          0
        ],
        "min": [
          2945,
          3427,
          0
        ]
      },
      "type": "move"
    },
    {
      "cost_ms": 600,
      "to": {
        "max": [
          2945,
          3426,
          0
        ],
        "min": [
          2945,
          3426,
          0
        ]
      },
      "type": "move"
    },
    {
      "cost_ms": 600,
      "to": {
        "max": [
          2945,
          3425,
          0
        ],
        "min": [
          2945,
          3425,
          0
        ]
      },
      "type": "move"
    },
    {
      "cost_ms": 600,
      "to": {
        "max": [
          2945,
          3424,
          0
        ],
        "min": [
          2945,
          3424,
          0
        ]
      },
      "type": "move"
    },
    {
      "cost_ms": 600,
      "to": {
        "max": [
          2945,
          3423,
          0
        ],
        "min": [
          2945,
          3423,
          0
        ]
      },
      "type": "move"
    },
    {
      "cost_ms": 600,
      "to": {
        "max": [
          2945,
          3422,
          0
        ],
        "min": [
          2945,
          3422,
          0
        ]
      },
      "type": "move"
    },
    {
      "cost_ms": 600,
      "to": {
        "max": [
          2946,
          3422,
          0
        ],
        "min": [
          2946,
          3422,
          0
        ]
      },
      "type": "move"
    },
    {
      "cost_ms": 600,
      "to": {
        "max": [
          2947,
          3422,
          0
        ],
        "min": [
          2947,
          3422,
          0
        ]
      },
      "type": "move"
    },
    {
      "cost_ms": 600,
      "to": {
        "max": [
          2948,
          3422,
          0
        ],
        "min": [
          2948,
          3422,
          0
        ]
      },
      "type": "move"
    },
    {
      "cost_ms": 600,
      "to": {
        "max": [
          2949,
          3422,
          0
        ],
        "min": [
          2949,
          3422,
          0
        ]
      },
      "type": "move"
    },
    {
      "cost_ms": 600,
      "to": {
        "max": [
          2949,
          3421,
          0
        ],
        "min": [
          2949,
          3421,
          0
        ]
      },
      "type": "move"
    },
    {
      "cost_ms": 600,
      "to": {
        "max": [
          2949,
          3420,
          0
        ],
        "min": [
          2949,
          3420,
          0
        ]
      },
      "type": "move"
    },
    {
      "cost_ms": 600,
      "to": {
        "max": [
          2949,
          3419,
          0
        ],
        "min": [
          2949,
          3419,
          0
        ]
      },
      "type": "move"
    },
    {
      "cost_ms": 600,
      "to": {
        "max": [
          2949,
          3418,
          0
        ],
        "min": [
          2949,
          3418,
          0
        ]
      },
      "type": "move"
    },
    {
      "cost_ms": 600,
      "to": {
        "max": [
          2950,
          3418,
          0
        ],
        "min": [
          2950,
          3418,
          0
        ]
      },
      "type": "move"
    },
    {
      "cost_ms": 600,
      "to": {
        "max": [
          2951,
          3418,
          0
        ],
        "min": [
          2951,
          3418,
          0
        ]
      },
      "type": "move"
    },
    {
      "cost_ms": 600,
      "to": {
        "max": [
          2952,
          3418,
          0
        ],
        "min": [
          2952,
          3418,
          0
        ]
      },
      "type": "move"
    },
    {
      "cost_ms": 600,
      "to": {
        "max": [
          2953,
          3418,
          0
        ],
        "min": [
          2953,
          3418,
          0
        ]
      },
      "type": "move"
    },
    {
      "cost_ms": 600,
      "to": {
        "max": [
          2954,
          3418,
          0
        ],
        "min": [
          2954,
          3418,
          0
        ]
      },
      "type": "move"
    },
    {
      "cost_ms": 600,
      "to": {
        "max": [
          2955,
          3418,
          0
        ],
        "min": [
          2955,
          3418,
          0
        ]
      },
      "type": "move"
    },
    {
      "cost_ms": 600,
      "to": {
        "max": [
          2956,
          3418,
          0
        ],
        "min": [
          2956,
          3418,
          0
        ]
      },
      "type": "move"
    },
    {
      "cost_ms": 600,
      "to": {
        "max": [
          2957,
          3418,
          0
        ],
        "min": [
          2957,
          3418,
          0
        ]
      },
      "type": "move"
    }
  ]
}